django_devbar/__init__.py
django_devbar/conf.py
django_devbar/middleware.py
django_devbar/templates/django_devbar/devbar.html
django_devbar/templates/django_devbar/duplicates.html
django_devbar/templates/django_devbar/similar.html
django_devbar/tracker.py
django_devbar-0.6.1.dist-info/WHEEL
django_devbar-0.6.1.dist-info/METADATA
django_devbar-0.6.1.dist-info/RECORD
