Metadata-Version: 2.4
Name: django-devbar
Version: 0.6.1
Summary: Lightweight performance devbar for Django
Keywords: django,debug,performance,monitoring,development
Author: amureki
Author-email: amureki <oss@amureki.me>
License-Expression: MIT
Classifier: Programming Language :: Python
Classifier: Programming Language :: Python :: 3
Classifier: Programming Language :: Python :: 3 :: Only
Classifier: Programming Language :: Python :: 3.10
Classifier: Programming Language :: Python :: 3.11
Classifier: Programming Language :: Python :: 3.12
Classifier: Programming Language :: Python :: 3.13
Classifier: Programming Language :: Python :: 3.14
Classifier: Framework :: Django
Classifier: Framework :: Django :: 4.2
Classifier: Framework :: Django :: 5.0
Classifier: Framework :: Django :: 5.1
Classifier: Framework :: Django :: 5.2
Classifier: Framework :: Django :: 6.0
Classifier: Topic :: Software Development
Classifier: Intended Audience :: Developers
Requires-Dist: django>=4.2
Requires-Python: >=3.10
Project-URL: Homepage, https://github.com/amureki/django-devbar
Project-URL: Issues, https://github.com/amureki/django-devbar/issues
Project-URL: Repository, https://github.com/amureki/django-devbar
